Metadata-Version: 2.1
Name: odoo12-addon-crm-stage-multi-company
Version: 12.0.1.0.0.99.dev10
Summary: This module adds support for multi company on crm stage.
Home-page: https://github.com/OCA/multi-company
Author: ACS0NE SA/NV, Odoo Community Association (OCA)
Author-email: support@odoo-community.org
License: AGPL-3
Platform: UNKNOWN
Classifier: Programming Language :: Python
Classifier: Framework :: Odoo
Classifier: License :: OSI Approved :: GNU Affero General Public License v3
Requires-Python: >=3.5
Requires-Dist: odoo (<12.1dev,>=12.0a)
